pandukabhaya/__init__.py
pandukabhaya/cli.py
pandukabhaya/converter.py
pandukabhaya/mappings/fm_abhaya.json
pandukabhaya-1.0.1.dist-info/LICENSE
pandukabhaya-1.0.1.dist-info/METADATA
pandukabhaya-1.0.1.dist-info/WHEEL
pandukabhaya-1.0.1.dist-info/entry_points.txt
pandukabhaya-1.0.1.dist-info/top_level.txt
pandukabhaya-1.0.1.dist-info/RECORD
