Metadata-Version: 2.2
Name: pandukabhaya
Version: 1.0.1
Summary: An ASCII to Unicode text converter for 'FM Abhaya' Sinhala font, with extensibility for other fonts via JSON mappings.
Home-page: https://github.com/akuruAI/Pandukabhaya
Author: akuruAI
Classifier: Programming Language :: Python :: 3
Classifier: License :: OSI Approved :: MIT License
Classifier: Operating System :: OS Independent
Requires-Python: >=3.6
License-File: LICENSE
Dynamic: author
Dynamic: classifier
Dynamic: description
Dynamic: description-content-type
Dynamic: home-page
Dynamic: requires-python
Dynamic: summary
